ADC_Model_TB.v
`timescale 1ns/1ps

// =====================================================================
//  TX: serial stream generator
// =====================================================================
module adc_stream_gen #(
    parameter integer N_AMPS       = 64,
    parameter integer N_ADC_PER_GP = 4,
    parameter integer ADC_BITS     = 12,
    parameter integer ZERO_CYCLES  = 16,
    parameter integer DATA_CYCLES  = 48,
    parameter integer GROUP_CYCLES = 64,
    parameter integer N_GROUPS     = 16,
    parameter integer FRAME_CYCLES = 1024,
    parameter integer TEST_ITERS   = 3
)(
    input  wire clk,
    input  wire rst_n,
    output reg  sync,
    output reg  next_amps,
    output reg  data
);

    // -------------------- storage --------------------
    reg [ADC_BITS-1:0] amp [0:TEST_ITERS-1][0:N_AMPS-1];

    integer t_init, i_init;
    initial begin
        for (t_init = 0; t_init < TEST_ITERS; t_init = t_init + 1)
            for (i_init = 0; i_init < N_AMPS; i_init = i_init + 1)
                amp[t_init][i_init] = $random & ((1<<ADC_BITS)-1);
    end

    // -------------------- state --------------------
    integer frame_cyc;
    reg [31:0] test_idx;     // generous width; trivial

    // -------------------- combinational next-state --------------------
    reg        sync_n, next_amps_n, data_n;
    integer    group_idx, cyc_in_group;
    integer    bit_idx, which_adc, which_bit, amp_index;
    integer    frame_cyc_n;
    reg [31:0] test_idx_n;

    always @* begin
        group_idx    = frame_cyc / GROUP_CYCLES;
        cyc_in_group = frame_cyc % GROUP_CYCLES;

        sync_n      = (frame_cyc < GROUP_CYCLES);
        next_amps_n = (cyc_in_group == 0);

        if (cyc_in_group < ZERO_CYCLES) begin
            bit_idx   = 0;
            which_adc = 0;
            which_bit = 0;
            amp_index = 0;
            data_n    = 1'b0;
        end else begin
            bit_idx   = cyc_in_group - ZERO_CYCLES;
            which_adc = bit_idx % N_ADC_PER_GP;
            which_bit = bit_idx / N_ADC_PER_GP;
            amp_index = N_ADC_PER_GP * group_idx + which_adc;
            data_n    = amp[test_idx][amp_index][which_bit];
        end

        frame_cyc_n = (frame_cyc == FRAME_CYCLES-1) ? 0 : frame_cyc + 1;

        if (frame_cyc == FRAME_CYCLES-1)
            test_idx_n = (test_idx == TEST_ITERS-1) ? 0 : test_idx + 1;
        else
            test_idx_n = test_idx;
    end

    // -------------------- sequential: register outputs --------------------
    always @(negedge clk or negedge rst_n) begin
        if (!rst_n) begin
            frame_cyc <= 0;
            sync      <= 1'b0;
            next_amps <= 1'b0;
            data      <= 1'b0;
            test_idx  <= 0;
        end else begin
            frame_cyc <= frame_cyc_n;
            sync      <= sync_n;
            next_amps <= next_amps_n;
            data      <= data_n;
            test_idx  <= test_idx_n;
        end
    end

endmodule


// =====================================================================
//  RX: deserialize the stream
// =====================================================================
module adc_rx #(
    parameter integer N_AMPS       = 64,
    parameter integer N_ADC_PER_GP = 4,
    parameter integer ADC_BITS     = 12,
    parameter integer ZERO_CYCLES  = 16,
    parameter integer GROUP_CYCLES = 64,
    parameter integer N_GROUPS     = 16
)(
    input  wire clk,
    input  wire rst_n,
    input  wire sync,
    input  wire next_amps,
    input  wire data,
    output reg  [ADC_BITS-1:0] amp_out [0:N_AMPS-1],
    output reg  frame_done
);
    // Strategy: a per-group cycle counter (0..GROUP_CYCLES-1) driven by
    // next_amps rising edge to reset, and a group index driven by next_amps
    // count. Frame start = sync rising edge.
    integer cyc_in_group;
    integer group_idx;
    integer bit_idx, which_adc, which_bit, amp_index;
    reg     next_amps_d, sync_d;
    integer k_init;

    initial begin
        for (k_init = 0; k_init < N_AMPS; k_init = k_init + 1)
            amp_out[k_init] = 0;
    end

    always @(posedge clk or negedge rst_n) begin
        if (!rst_n) begin
            cyc_in_group <= 0;
            group_idx    <= 0;
            next_amps_d  <= 1'b0;
            sync_d       <= 1'b0;
            frame_done   <= 1'b0;
        end else begin
            next_amps_d <= next_amps;
            sync_d      <= sync;

            // On next_amps rising edge: reset cyc_in_group, advance group.
            // On sync rising edge: also reset group_idx to 0.
            if (sync & ~sync_d) begin
                group_idx    <= 0;
                cyc_in_group <= 1;   // we ARE consuming cycle 0 right now
            end else if (next_amps & ~next_amps_d) begin
                group_idx    <= group_idx + 1;
                cyc_in_group <= 1;
            end else begin
                cyc_in_group <= cyc_in_group + 1;
            end

            // Sample data when inside the data window of the current group.
            // Use combinational current cyc_in_group (not the about-to-update).
            if (cyc_in_group >= ZERO_CYCLES && cyc_in_group < GROUP_CYCLES) begin
                bit_idx   = cyc_in_group - ZERO_CYCLES;
                which_adc = bit_idx % N_ADC_PER_GP;
                which_bit = bit_idx / N_ADC_PER_GP;
                amp_index = N_ADC_PER_GP * group_idx + which_adc;
                amp_out[amp_index][which_bit] <= data;
            end

            // Pulse frame_done at the end of the last group of the frame.
            frame_done <= (group_idx == N_GROUPS-1) &&
                          (cyc_in_group == GROUP_CYCLES-1);
        end
    end
endmodule


// =====================================================================
//  Testbench top
// =====================================================================
module tb_adc_stream;

    localparam integer N_AMPS       = 64;
    localparam integer N_ADC_PER_GP = 4;
    localparam integer ADC_BITS     = 12;
    localparam integer ZERO_CYCLES  = 16;
    localparam integer GROUP_CYCLES = 64;
    localparam integer N_GROUPS     = 16;
    localparam integer FRAME_CYCLES = 1024;
    localparam integer TEST_ITERS   = 3;

    // 32 MHz -> 31.25 ns period. iverilog handles real delays fine.
    localparam real CLK_PERIOD = 31.25;

    reg  clk = 0;
    reg  rst_n = 0;
    wire sync, next_amps, data;
    wire [ADC_BITS-1:0] amp_out [0:N_AMPS-1];
    wire frame_done;

    always #(CLK_PERIOD/2) clk = ~clk;

    adc_stream_gen #(
        .N_AMPS(N_AMPS), .N_ADC_PER_GP(N_ADC_PER_GP), .ADC_BITS(ADC_BITS),
        .ZERO_CYCLES(ZERO_CYCLES), .GROUP_CYCLES(GROUP_CYCLES),
        .N_GROUPS(N_GROUPS), .FRAME_CYCLES(FRAME_CYCLES),
        .TEST_ITERS(TEST_ITERS)
    ) u_tx (
        .clk(clk), .rst_n(rst_n),
        .sync(sync), .next_amps(next_amps), .data(data)
    );

    adc_rx #(
        .N_AMPS(N_AMPS), .N_ADC_PER_GP(N_ADC_PER_GP), .ADC_BITS(ADC_BITS),
        .ZERO_CYCLES(ZERO_CYCLES), .GROUP_CYCLES(GROUP_CYCLES),
        .N_GROUPS(N_GROUPS)
    ) u_rx (
        .clk(clk), .rst_n(rst_n),
        .sync(sync), .next_amps(next_amps), .data(data),
        .amp_out(amp_out), .frame_done(frame_done)
    );

    integer errors         = 0;
    integer compares       = 0;
    integer frames_checked = 0;
    integer t;

    // Wait helper instead of @(posedge clk iff ...) which iverilog dislikes
    task wait_frame_done;
        begin
            @(posedge clk);
            while (!frame_done) @(posedge clk);
        end
    endtask

    task check_frame(input integer iter);
        integer i;
        reg [ADC_BITS-1:0] exp_v, got_v;
        begin
            for (i = 0; i < N_AMPS; i = i + 1) begin
                exp_v = u_tx.amp[iter][i];
                got_v = amp_out[i];
                compares = compares + 1;
                if (exp_v !== got_v) begin
                    errors = errors + 1;
                    if (errors <= 20)
                        $display("[t=%0t] MISMATCH iter=%0d amp[%0d]: exp=0x%0h got=0x%0h",
                                 $time, iter, i, exp_v, got_v);
                end
            end
            $display("[t=%0t] frame %0d checked (%0d amps, errors so far=%0d)",
                     $time, iter, N_AMPS, errors);
        end
    endtask

    initial begin
        $dumpfile("tb_adc_stream.vcd");
        $dumpvars(0, tb_adc_stream);

        rst_n = 0;
        repeat (4) @(posedge clk);
        rst_n = 1;

        for (t = 0; t < TEST_ITERS; t = t + 1) begin
            wait_frame_done();
            #1;
            check_frame(t);
            frames_checked = frames_checked + 1;
        end

        $display("--------------------------------------------------");
        $display("Frames checked : %0d / %0d", frames_checked, TEST_ITERS);
        $display("Comparisons    : %0d", compares);
        $display("Errors         : %0d", errors);
        if (errors == 0) $display("RESULT: PASS");
        else             $display("RESULT: FAIL");
        $display("--------------------------------------------------");
        $finish;
    end

    initial begin
        #(CLK_PERIOD * FRAME_CYCLES * (TEST_ITERS + 2));
        $display("TIMEOUT");
        $display("Errors so far: %0d", errors);
        $finish;
    end

endmodule

tb_adc_stream.vcd
$date
	Fri May 22 15:47:04 2026
$end
$version
	Icarus Verilog
$end
$timescale
	1ps
$end
$scope module tb_adc_stream $end
$var wire 1 ! sync $end
$var wire 1 " next_amps $end
$var wire 1 # frame_done $end
$var wire 1 $ data $end
$var wire 768 % amp_out [767:0] $end
$var parameter 32 & ADC_BITS $end
$var real 1 ' CLK_PERIOD $end
$var parameter 32 ( FRAME_CYCLES $end
$var parameter 32 ) GROUP_CYCLES $end
$var parameter 32 * N_ADC_PER_GP $end
$var parameter 32 + N_AMPS $end
$var parameter 32 , N_GROUPS $end
$var parameter 32 - TEST_ITERS $end
$var parameter 32 . ZERO_CYCLES $end
$var reg 1 / clk $end
$var reg 1 0 rst_n $end
$var integer 32 1 compares [31:0] $end
$var integer 32 2 errors [31:0] $end
$var integer 32 3 frames_checked [31:0] $end
$var integer 32 4 t [31:0] $end
$scope module u_rx $end
$var wire 1 / clk $end
$var wire 1 0 rst_n $end
$var wire 1 ! sync $end
$var wire 1 " next_amps $end
$var wire 1 $ data $end
$var parameter 32 5 ADC_BITS $end
$var parameter 32 6 GROUP_CYCLES $end
$var parameter 32 7 N_ADC_PER_GP $end
$var parameter 32 8 N_AMPS $end
$var parameter 32 9 N_GROUPS $end
$var parameter 32 : ZERO_CYCLES $end
$var reg 768 ; amp_out [767:0] $end
$var reg 1 # frame_done $end
$var reg 1 < next_amps_d $end
$var reg 1 = sync_d $end
$var integer 32 > amp_index [31:0] $end
$var integer 32 ? bit_idx [31:0] $end
$var integer 32 @ cyc_in_group [31:0] $end
$var integer 32 A group_idx [31:0] $end
$var integer 32 B k_init [31:0] $end
$var integer 32 C which_adc [31:0] $end
$var integer 32 D which_bit [31:0] $end
$upscope $end
$scope module u_tx $end
$var wire 1 / clk $end
$var wire 1 0 rst_n $end
$var parameter 32 E ADC_BITS $end
$var parameter 32 F DATA_CYCLES $end
$var parameter 32 G FRAME_CYCLES $end
$var parameter 32 H GROUP_CYCLES $end
$var parameter 32 I N_ADC_PER_GP $end
$var parameter 32 J N_AMPS $end
$var parameter 32 K N_GROUPS $end
$var parameter 32 L TEST_ITERS $end
$var parameter 32 M ZERO_CYCLES $end
$var reg 1 $ data $end
$var reg 1 N data_n $end
$var reg 1 " next_amps $end
$var reg 1 O next_amps_n $end
$var reg 1 ! sync $end
$var reg 1 P sync_n $end
$var reg 32 Q test_idx [31:0] $end
$var reg 32 R test_idx_n [31:0] $end
$var integer 32 S amp_index [31:0] $end
$var integer 32 T bit_idx [31:0] $end
$var integer 32 U cyc_in_group [31:0] $end
$var integer 32 V frame_cyc [31:0] $end
$var integer 32 W frame_cyc_n [31:0] $end
$var integer 32 X group_idx [31:0] $end
$var integer 32 Y i_init [31:0] $end
$var integer 32 Z t_init [31:0] $end
$var integer 32 [ which_adc [31:0] $end
$var integer 32 \ which_bit [31:0] $end
$upscope $end
$scope task check_frame $end
$var reg 12 ] exp_v [11:0] $end
$var reg 12 ^ got_v [11:0] $end
$var integer 32 _ i [31:0] $end
$var integer 32 ` iter [31:0] $end
$upscope $end
$scope task wait_frame_done $end
$upscope $end
$upscope $end
$enddefinitions $end
$comment Show the parameter values. $end
$dumpall
b10000 M
b11 L
b10000 K
b1000000 J
b100 I
b1000000 H
b10000000000 G
b110000 F
b1100 E
b10000 :
b10000 9
b1000000 8
b100 7
b1000000 6
b1100 5
b10000 .
b11 -
b10000 ,
b1000000 +
b100 *
b1000000 )
b10000000000 (
r31.25 '
b1100 &
$end
#0
$dumpvars
bx `
bx _
bx ^
bx ]
bx \
bx [
b11 Z
b1000000 Y
bx X
bx W
bx V
bx U
bx T
bx S
bx R
bx Q
xP
xO
xN
bx D
bx C
b1000000 B
bx A
bx @
bx ?
bx >
x=
x<
b0 ;
bx 4
b0 3
b0 2
b0 1
00
0/
b0 %
x$
x#
x"
x!
$end
#15625
0#
0=
0<
b0 A
b0 @
1/
#31250
b0 R
b1 W
0N
b0 S
b0 \
b0 [
b0 T
1O
1P
b0 U
b0 X
b0 Q
0$
0"
0!
b0 V
0/
#46875
1/
#62500
0/
#78125
1/
#93750
0/
#109375
b1 @
b0 4
10
1/
#125000
b10 W
0O
b1 U
1"
1!
b1 V
0/
#140625
1=
1<
1/
#156250
b11 W
b10 U
0"
b10 V
0/
#171875
b10 @
0<
1/
#187500
b100 W
b11 U
b11 V
0/
#203125
b11 @
1/
#218750
b101 W
b100 U
b100 V
0/
#234375
b100 @
1/
#250000
b110 W
b101 U
b101 V
0/
#265625
b101 @
1/
#281250
b111 W
b110 U
b110 V
0/
#296875
b110 @
1/
#312500
b1000 W
b111 U
b111 V
0/
#328125
b111 @
1/
#343750
b1001 W
b1000 U
b1000 V
0/
#359375
b1000 @
1/
#375000
b1010 W
b1001 U
b1001 V
0/
#390625
b1001 @
1/
#406250
b1011 W
b1010 U
b1010 V
0/
#421875
b1010 @
1/
#437500
b1100 W
b1011 U
b1011 V
0/
#453125
b1011 @
1/
#468750
b1101 W
b1100 U
b1100 V
0/
#484375
b1100 @
1/
#500000
b1110 W
b1101 U
b1101 V
0/
#515625
b1101 @
1/
#531250
b1111 W
b1110 U
b1110 V
0/
#546875
b1110 @
1/
#562500
b10000 W
b1111 U
b1111 V
0/
#578125
b1111 @
1/
#593750
b10001 W
b10000 U
b10000 V
0/
#609375
b10000 @
1/
#625000
b10010 W
1N
b1 S
b1 [
b1 T
b10001 U
b10001 V
0/
#640625
b10001 @
b0 >
b0 D
b0 C
b0 ?
1/
#656250
b10011 W
0N
b10 S
b10 [
b10 T
b10010 U
1$
b10010 V
0/
#671875
b1000000000000 %
b1000000000000 ;
b10010 @
b1 >
b1 C
b1 ?
1/
#687500
b10100 W
1N
b11 S
b11 [
b11 T
b10011 U
0$
b10011 V
0/
#703125
b10011 @
b10 >
b10 C
b10 ?
1/
#718750
b10101 W
0N
b0 S
b1 \
b0 [
b100 T
b10100 U
1$
b10100 V
0/
#734375
b1000000000000000000000001000000000000 %
b1000000000000000000000001000000000000 ;
b10100 @
b11 >
b11 C
b11 ?
1/
#750000
b10110 W
1N
b1 S
b1 [
b101 T
b10101 U
0$
b10101 V
0/
#765625
b10101 @
b0 >
b1 D
b0 C
b100 ?
1/
#781250
b10111 W
b10 S
b10 [
b110 T
b10110 U
1$
b10110 V
0/
#796875
b1000000000000000000000011000000000000 %
b1000000000000000000000011000000000000 ;
b10110 @
b1 >
b1 C
b101 ?
1/
#812500
b11000 W
0N
b11 S
b11 [
b111 T
b10111 U
b10111 V
0/
#828125
b1000000000010000000000011000000000000 %
b1000000000010000000000011000000000000 ;
b10111 @
b10 >
b10 C
b110 ?
1/
#843750
b11001 W
1N
b0 S
b10 \
b0 [
b1000 T
b11000 U
0$
b11000 V
0/
#859375
b11000 @
b11 >
b11 C
b111 ?
1/
#875000
b11010 W
b1 S
b1 [
b1001 T
b11001 U
1$
b11001 V
0/
#890625
b1000000000010000000000011000000000100 %
b1000000000010000000000011000000000100 ;
b11001 @
b0 >
b10 D
b0 C
b1000 ?
1/
#906250
b11011 W
0N
b10 S
b10 [
b1010 T
b11010 U
b11010 V
0/
#921875
b1000000000010000000000111000000000100 %
b1000000000010000000000111000000000100 ;
b11010 @
b1 >
b1 C
b1001 ?
1/
#937500
b11100 W
1N
b11 S
b11 [
b1011 T
b11011 U
0$
b11011 V
0/
#953125
b11011 @
b10 >
b10 C
b1010 ?
1/
#968750
b11101 W
0N
b0 S
b11 \
b0 [
b1100 T
b11100 U
1$
b11100 V
0/
#984375
b101000000000010000000000111000000000100 %
b101000000000010000000000111000000000100 ;
b11100 @
b11 >
b11 C
b1011 ?
1/
#1000000
b11110 W
1N
b1 S
b1 [
b1101 T
b11101 U
0$
b11101 V
0/
#1015625
b11101 @
b0 >
b11 D
b0 C
b1100 ?
1/
#1031250
b11111 W
b10 S
b10 [
b1110 T
b11110 U
1$
b11110 V
0/
#1046875
b101000000000010000000001111000000000100 %
b101000000000010000000001111000000000100 ;
b11110 @
b1 >
b1 C
b1101 ?
1/
#1062500
b100000 W
0N
b11 S
b11 [
b1111 T
b11111 U
b11111 V
0/
#1078125
b101000000001010000000001111000000000100 %
b101000000001010000000001111000000000100 ;
b11111 @
b10 >
b10 C
b1110 ?
1/
#1093750
b100001 W
1N
b0 S
b100 \
b0 [
b10000 T
b100000 U
0$
b100000 V
0/
#1109375
b100000 @
b11 >
b11 C
b1111 ?
1/
#1125000
b100010 W
0N
b1 S
b1 [
b10001 T
b100001 U
1$
b100001 V
0/
#1140625
b101000000001010000000001111000000010100 %
b101000000001010000000001111000000010100 ;
b100001 @
b0 >
b100 D
b0 C
b10000 ?
1/
#1156250
b100011 W
b10 S
b10 [
b10010 T
b100010 U
0$
b100010 V
0/
#1171875
b100010 @
b1 >
b1 C
b10001 ?
1/
#1187500
b100100 W
b11 S
b11 [
b10011 T
b100011 U
b100011 V
0/
#1203125
b100011 @
b10 >
b10 C
b10010 ?
1/
#1218750
b100101 W
b0 S
b101 \
b0 [
b10100 T
b100100 U
b100100 V
0/
#1234375
b100100 @
b11 >
b11 C
b10011 ?
1/
#1250000
b100110 W
1N
b1 S
b1 [
b10101 T
b100101 U
b100101 V
0/
#1265625
b100101 @
b0 >
b101 D
b0 C
b10100 ?
1/
#1281250
b100111 W
0N
b10 S
b10 [
b10110 T
b100110 U
1$
b100110 V
0/
#1296875
b101000000001010000000101111000000010100 %
b101000000001010000000101111000000010100 ;
b100110 @
b1 >
b1 C
b10101 ?
1/
#1312500
b101000 W
1N
b11 S
b11 [
b10111 T
b100111 U
0$
b100111 V
0/
#1328125
b100111 @
b10 >
b10 C
b10110 ?
1/
#1343750
b101001 W
b0 S
b110 \
b0 [
b11000 T
b101000 U
1$
b101000 V
0/
#1359375
b100101000000001010000000101111000000010100 %
b100101000000001010000000101111000000010100 ;
b101000 @
b11 >
b11 C
b10111 ?
1/
#1375000
b101010 W
b1 S
b1 [
b11001 T
b101001 U
b101001 V
0/
#1390625
b100101000000001010000000101111000001010100 %
b100101000000001010000000101111000001010100 ;
b101001 @
b0 >
b110 D
b0 C
b11000 ?
1/
#1406250
b101011 W
0N
b10 S
b10 [
b11010 T
b101010 U
b101010 V
0/
#1421875
b100101000000001010000001101111000001010100 %
b100101000000001010000001101111000001010100 ;
b101010 @
b1 >
b1 C
b11001 ?
1/
#1437500
b101100 W
b11 S
b11 [
b11011 T
b101011 U
0$
b101011 V
0/
#1453125
b101011 @
b10 >
b10 C
b11010 ?
1/
#1468750
b101101 W
1N
b0 S
b111 \
b0 [
b11100 T
b101100 U
b101100 V
0/
#1484375
b101100 @
b11 >
b11 C
b11011 ?
1/
#1500000
b101110 W
0N
b1 S
b1 [
b11101 T
b101101 U
1$
b101101 V
0/
#1515625
b100101000000001010000001101111000011010100 %
b100101000000001010000001101111000011010100 ;
b101101 @
b0 >
b111 D
b0 C
b11100 ?
1/
#1531250
b101111 W
b10 S
b10 [
b11110 T
b101110 U
0$
b101110 V
0/
#1546875
b101110 @
b1 >
b1 C
b11101 ?
1/
#1562500
b110000 W
1N
b11 S
b11 [
b11111 T
b101111 U
b101111 V
0/
#1578125
b101111 @
b10 >
b10 C
b11110 ?
1/
#1593750
b110001 W
0N
b0 S
b1000 \
b0 [
b100000 T
b110000 U
1$
b110000 V
0/
#1609375
b10100101000000001010000001101111000011010100 %
b10100101000000001010000001101111000011010100 ;
b110000 @
b11 >
b11 C
b11111 ?
1/
#1625000
b110010 W
b1 S
b1 [
b100001 T
b110001 U
0$
b110001 V
0/
#1640625
b110001 @
b0 >
b1000 D
b0 C
b100000 ?
1/
#1656250
b110011 W
b10 S
b10 [
b100010 T
b110010 U
b110010 V
0/
#1671875
b110010 @
b1 >
b1 C
b100001 ?
1/
#1687500
b110100 W
1N
b11 S
b11 [
b100011 T
b110011 U
b110011 V
0/
#1703125
b110011 @
b10 >
b10 C
b100010 ?
1/
#1718750
b110101 W
0N
b0 S
b1001 \
b0 [
b100100 T
b110100 U
1$
b110100 V
0/
#1734375
b110100101000000001010000001101111000011010100 %
b110100101000000001010000001101111000011010100 ;
b110100 @
b11 >
b11 C
b100011 ?
1/
#1750000
b110110 W
b1 S
b1 [
b100101 T
b110101 U
0$
b110101 V
0/
#1765625
b110101 @
b0 >
b1001 D
b0 C
b100100 ?
1/
#1781250
b110111 W
b10 S
b10 [
b100110 T
b110110 U
b110110 V
0/
#1796875
b110110 @
b1 >
b1 C
b100101 ?
1/
#1812500
b111000 W
1N
b11 S
b11 [
b100111 T
b110111 U
b110111 V
0/
#1828125
b110111 @
b10 >
b10 C
b100110 ?
1/
#1843750
b111001 W
0N
b0 S
b1010 \
b0 [
b101000 T
b111000 U
1$
b111000 V
0/
#1859375
b1110100101000000001010000001101111000011010100 %
b1110100101000000001010000001101111000011010100 ;
b111000 @
b11 >
b11 C
b100111 ?
1/
#1875000
b111010 W
1N
b1 S
b1 [
b101001 T
b111001 U
0$
b111001 V
0/
#1890625
b111001 @
b0 >
b1010 D
b0 C
b101000 ?
1/
#1906250
b111011 W
0N
b10 S
b10 [
b101010 T
b111010 U
1$
b111010 V
0/
#1921875
b1110100101000000001010010001101111000011010100 %
b1110100101000000001010010001101111000011010100 ;
b111010 @
b1 >
b1 C
b101001 ?
1/
#1937500
b111100 W
b11 S
b11 [
b101011 T
b111011 U
0$
b111011 V
0/
#1953125
b111011 @
b10 >
b10 C
b101010 ?
1/
#1968750
b111101 W
b0 S
b1011 \
b0 [
b101100 T
b111100 U
b111100 V
0/
#1984375
b111100 @
b11 >
b11 C
b101011 ?
1/
#2000000
b111110 W
1N
b1 S
b1 [
b101101 T
b111101 U
b111101 V
0/
#2015625
b111101 @
b0 >
b1011 D
b0 C
b101100 ?
1/
#2031250
b111111 W
b10 S
b10 [
b101110 T
b111110 U
1$
b111110 V
0/
#2046875
b1110100101000000001010110001101111000011010100 %
b1110100101000000001010110001101111000011010100 ;
b111110 @
b1 >
b1 C
b101101 ?
1/
#2062500
b1000000 W
0N
b11 S
b11 [
b101111 T
b111111 U
b111111 V
0/
#2078125
b1110100101100000001010110001101111000011010100 %
b1110100101100000001010110001101111000011010100 ;
b111111 @
b10 >
b10 C
b101110 ?
1/
#2093750
b1000001 W
b0 S
b0 \
b0 [
b0 T
1O
0P
b0 U
b1 X
0$
b1000000 V
0/
#2109375
b1000000 @
b11 >
b11 C
b101111 ?
1/
#2125000
b1000010 W
0O
b1 U
1"
0!
b1000001 V
0/
#2140625
b1 @
b1 A
0=
1<
1/
#2156250
b1000011 W
b10 U
0"
b1000010 V
0/
#2171875
b10 @
0<
1/
#2187500
b1000100 W
b11 U
b1000011 V
0/
#2203125
b11 @
1/
#2218750
b1000101 W
b100 U
b1000100 V
0/
#2234375
b100 @
1/
#2250000
b1000110 W
b101 U
b1000101 V
0/
#2265625
b101 @
1/
#2281250
b1000111 W
b110 U
b1000110 V
0/
#2296875
b110 @
1/
#2312500
b1001000 W
b111 U
b1000111 V
0/
#2328125
b111 @
1/
#2343750
b1001001 W
b1000 U
b1001000 V
0/
#2359375
b1000 @
1/
#2375000
b1001010 W
b1001 U
b1001001 V
0/
#2390625
b1001 @
1/
#2406250
b1001011 W
b1010 U
b1001010 V
0/
#2421875
b1010 @
1/
#2437500
b1001100 W
b1011 U
b1001011 V
0/
#2453125
b1011 @
1/
#2468750
b1001101 W
b1100 U
b1001100 V
0/
#2484375
b1100 @
1/
#2500000
b1001110 W
b1101 U
b1001101 V
0/
#2515625
b1101 @
1/
#2531250
b1001111 W
b1110 U
b1001110 V
0/
#2546875
b1110 @
1/
#2562500
b1010000 W
b1111 U
b1001111 V
0/
#2578125
b1111 @
1/
#2593750
b1010001 W
b100 S
b10000 U
b1010000 V
0/
#2609375
b10000 @
1/
#2625000
b1010010 W
1N
b101 S
b1 [
b1 T
b10001 U
b1010001 V
0/
#2640625
b10001 @
b100 >
b0 D
b0 C
b0 ?
1/
#2656250
b1010011 W
0N
b110 S
b10 [
b10 T
b10010 U
1$
b1010010 V
0/
#2671875
b1000000000000001110100101100000001010110001101111000011010100 %
b1000000000000001110100101100000001010110001101111000011010100 ;
b10010 @
b101 >
b1 C
b1 ?
1/
#2687500
b1010100 W
1N
b111 S
b11 [
b11 T
b10011 U
0$
b1010011 V
0/
#2703125
b10011 @
b110 >
b10 C
b10 ?
1/
#2718750
b1010101 W
0N
b100 S
b1 \
b0 [
b100 T
b10100 U
1$
b1010100 V
0/
#2734375
b1000000000000000000000001000000000000001110100101100000001010110001101111000011010100 %
b1000000000000000000000001000000000000001110100101100000001010110001101111000011010100 ;
b10100 @
b111 >
b11 C
b11 ?
1/
#2750000
b1010110 W
1N
b101 S
b1 [
b101 T
b10101 U
0$
b1010101 V
0/
#2765625
b10101 @
b100 >
b1 D
b0 C
b100 ?
1/
#2781250
b1010111 W
b110 S
b10 [
b110 T
b10110 U
1$
b1010110 V
0/
#2796875
b1000000000000000000000011000000000000001110100101100000001010110001101111000011010100 %
b1000000000000000000000011000000000000001110100101100000001010110001101111000011010100 ;
b10110 @
b101 >
b1 C
b101 ?
1/
#2812500
b1011000 W
0N
b111 S
b11 [
b111 T
b10111 U
b1010111 V
0/
#2828125
b1000000000010000000000011000000000000001110100101100000001010110001101111000011010100 %
b1000000000010000000000011000000000000001110100101100000001010110001101111000011010100 ;
b10111 @
b110 >
b10 C
b110 ?
1/
#2843750
b1011001 W
b100 S
b10 \
b0 [
b1000 T
b11000 U
0$
b1011000 V
0/
#2859375
b11000 @
b111 >
b11 C
b111 ?
1/
#2875000
b1011010 W
b101 S
b1 [
b1001 T
b11001 U
b1011001 V
0/
#2890625
b11001 @
b100 >
b10 D
b0 C
b1000 ?
1/
#2906250
b1011011 W
1N
b110 S
b10 [
b1010 T
b11010 U
b1011010 V
0/
#2921875
b11010 @
b101 >
b1 C
b1001 ?
1/
#2937500
b1011100 W
0N
b111 S
b11 [
b1011 T
b11011 U
1$
b1011011 V
0/
#2953125
b1000000000110000000000011000000000000001110100101100000001010110001101111000011010100 %
b1000000000110000000000011000000000000001110100101100000001010110001101111000011010100 ;
b11011 @
b110 >
b10 C
b1010 ?
1/
#2968750
b1011101 W
b100 S
b11 \
b0 [
b1100 T
b11100 U
0$
b1011100 V
0/
#2984375
b11100 @
b111 >
b11 C
b1011 ?
1/
#3000000
b1011110 W
1N
b101 S
b1 [
b1101 T
b11101 U
b1011101 V
0/
#3015625
b11101 @
b100 >
b11 D
b0 C
b1100 ?
1/
#3031250
b1011111 W
0N
b110 S
b10 [
b1110 T
b11110 U
1$
b1011110 V
0/
#3046875
b1000000000110000000001011000000000000001110100101100000001010110001101111000011010100 %
b1000000000110000000001011000000000000001110100101100000001010110001101111000011010100 ;
b11110 @
b101 >
b1 C
b1101 ?
1/
#3062500
b1100000 W
b111 S
b11 [
b1111 T
b11111 U
0$
b1011111 V
0/
#3078125
b11111 @
b110 >
b10 C
b1110 ?
1/
#3093750
b1100001 W
b100 S
b100 \
b0 [
b10000 T
b100000 U
b1100000 V
0/
#3109375
b100000 @
b111 >
b11 C
b1111 ?
1/
#3125000
b1100010 W
1N
b101 S
b1 [
b10001 T
b100001 U
b1100001 V
0/
#3140625
b100001 @
b100 >
b100 D
b0 C
b10000 ?
1/
#3156250
b1100011 W
b110 S
b10 [
b10010 T
b100010 U
1$
b1100010 V
0/
#3171875
b1000000000110000000011011000000000000001110100101100000001010110001101111000011010100 %
b1000000000110000000011011000000000000001110100101100000001010110001101111000011010100 ;
b100010 @
b101 >
b1 C
b10001 ?
1/
#3187500
b1100100 W
b111 S
b11 [
b10011 T
b100011 U
b1100011 V
0/
#3203125
b1000000010110000000011011000000000000001110100101100000001010110001101111000011010100 %
b1000000010110000000011011000000000000001110100101100000001010110001101111000011010100 ;
b100011 @
b110 >
b10 C
b10010 ?
1/
#3218750
b1100101 W
0N
b100 S
b101 \
b0 [
b10100 T
b100100 U
b1100100 V
0/
#3234375
b10001000000010110000000011011000000000000001110100101100000001010110001101111000011010100 %
b10001000000010110000000011011000000000000001110100101100000001010110001101111000011010100 ;
b100100 @
b111 >
b11 C
b10011 ?
1/
#3250000
b1100110 W
b101 S
b1 [
b10101 T
b100101 U
0$
b1100101 V
0/
#3265625
b100101 @
b100 >
b101 D
b0 C
b10100 ?
1/
#3281250
b1100111 W
1N
b110 S
b10 [
b10110 T
b100110 U
b1100110 V
0/
#3296875
b100110 @
b101 >
b1 C
b10101 ?
1/
#3312500
b1101000 W
0N
b111 S
b11 [
b10111 T
b100111 U
1$
b1100111 V
0/
#3328125
b10001000000110110000000011011000000000000001110100101100000001010110001101111000011010100 %
b10001000000110110000000011011000000000000001110100101100000001010110001101111000011010100 ;
b100111 @
b110 >
b10 C
b10110 ?
1/
#3343750
b1101001 W
1N
b100 S
b110 \
b0 [
b11000 T
b101000 U
0$
b1101000 V
0/
#3359375
b101000 @
b111 >
b11 C
b10111 ?
1/
#3375000
b1101010 W
b101 S
b1 [
b11001 T
b101001 U
1$
b1101001 V
0/
#3390625
b10001000000110110000000011011000001000000001110100101100000001010110001101111000011010100 %
b10001000000110110000000011011000001000000001110100101100000001010110001101111000011010100 ;
b101001 @
b100 >
b110 D
b0 C
b11000 ?
1/
#3406250
b1101011 W
b110 S
b10 [
b11010 T
b101010 U
b1101010 V
0/
#3421875
b10001000000110110000001011011000001000000001110100101100000001010110001101111000011010100 %
b10001000000110110000001011011000001000000001110100101100000001010110001101111000011010100 ;
b101010 @
b101 >
b1 C
b11001 ?
1/
#3437500
b1101100 W
0N
b111 S
b11 [
b11011 T
b101011 U
b1101011 V
0/
#3453125
b10001000001110110000001011011000001000000001110100101100000001010110001101111000011010100 %
b10001000001110110000001011011000001000000001110100101100000001010110001101111000011010100 ;
b101011 @
b110 >
b10 C
b11010 ?
1/
